{
  "classname": null,
  "name": null,
  "animation": {
    "classname": null,
    "name": "AnimationManager",
    "actionlist": []
  },
  "dataScale": 1,
  "designHeight": 206,
  "designWidth": 150,
  "textures": [
    "card_elem.plist"
  ],
  "version": "1.2.0.1",
  "widgetTree": {
    "classname": "Panel",
    "name": null,
    "children": [
      {
        "classname": "ImageView",
        "name": null,
        "children": [],
        "options": {
          "__type": "ComGUIImageViewSurrogate:#EditorCommon.JsonModel.Component.GUI",
          "classname": "ImageView",
          "name": "card_mask",
          "ZOrder": 1,
          "actiontag": 34,
          "anchorPointX": 0.5,
          "anchorPointY": 0.5,
          "classType": null,
          "colorB": 255,
          "colorG": 255,
          "colorR": 255,
          "flipX": false,
          "flipY": false,
          "height": 206,
          "ignoreSize": true,
          "layoutParameter": null,
          "opacity": 255,
          "positionPercentX": 0.5,
          "positionPercentY": 0.5,
          "positionType": 1,
          "rotation": 0,
          "scaleX": 1,
          "scaleY": 1,
          "sizePercentX": 0.533333361,
          "sizePercentY": 0.3883495,
          "sizeType": 0,
          "tag": 2,
          "touchAble": false,
          "useMergedTexture": false,
          "visible": true,
          "width": 150,
          "x": 75,
          "y": 103,
          "capInsetsHeight": 0,
          "capInsetsWidth": 0,
          "capInsetsX": 0,
          "capInsetsY": 0,
          "fileName": null,
          "fileNameData": {
            "path": "card_hero_mask_big.png",
            "plistFile": "card_elem.plist",
            "resourceType": 1
          },
          "scale9Enable": false,
          "scale9Height": 206,
          "scale9Width": 150
        }
      },
      {
        "classname": "ImageView",
        "name": null,
        "children": [],
        "options": {
          "__type": "ComGUIImageViewSurrogate:#EditorCommon.JsonModel.Component.GUI",
          "classname": "ImageView",
          "name": "icon_hp",
          "ZOrder": 2,
          "actiontag": 35,
          "anchorPointX": 0.5,
          "anchorPointY": 0.5,
          "classType": null,
          "colorB": 255,
          "colorG": 255,
          "colorR": 255,
          "flipX": false,
          "flipY": false,
          "height": 26,
          "ignoreSize": true,
          "layoutParameter": null,
          "opacity": 255,
          "positionPercentX": 0.8866669,
          "positionPercentY": 0.09550139,
          "positionType": 0,
          "rotation": 0,
          "scaleX": 1,
          "scaleY": 1,
          "sizePercentX": 0.533333361,
          "sizePercentY": 0.3883495,
          "sizeType": 0,
          "tag": 3,
          "touchAble": false,
          "useMergedTexture": false,
          "visible": true,
          "width": 20,
          "x": 133,
          "y": 19,
          "capInsetsHeight": 0,
          "capInsetsWidth": 0,
          "capInsetsX": 0,
          "capInsetsY": 0,
          "fileName": null,
          "fileNameData": {
            "path": "hp_icon_normal.png",
            "plistFile": "card_elem.plist",
            "resourceType": 1
          },
          "scale9Enable": false,
          "scale9Height": 26,
          "scale9Width": 20
        }
      },
      {
        "classname": "LabelAtlas",
        "name": null,
        "children": [],
        "options": {
          "__type": "ComGUILabelAtlasSurrogate:#EditorCommon.JsonModel.Component.GUI",
          "classname": "LabelAtlas",
          "name": "hp",
          "ZOrder": 2,
          "actiontag": 36,
          "anchorPointX": 0.5,
          "anchorPointY": 0.5,
          "classType": null,
          "colorB": 255,
          "colorG": 255,
          "colorR": 255,
          "flipX": false,
          "flipY": false,
          "height": 32,
          "ignoreSize": true,
          "layoutParameter": null,
          "opacity": 255,
          "positionPercentX": 0.8866669,
          "positionPercentY": 0.0760838,
          "positionType": 0,
          "rotation": 0,
          "scaleX": 0.7,
          "scaleY": 0.7,
          "sizePercentX": 1.6,
          "sizePercentY": 0.1553398,
          "sizeType": 0,
          "tag": 4,
          "touchAble": false,
          "useMergedTexture": false,
          "visible": true,
          "width": 48,
          "x": 133,
          "y": 15,
          "charMapFile": null,
          "charMapFileData": {
            "path": "GUI/labelatlasimg.png",
            "plistFile": null,
            "resourceType": 0
          },
          "itemHeight": 32,
          "itemWidth": 24,
          "startCharMap": "0",
          "stringValue": "11"
        }
      },
      {
        "classname": "ImageView",
        "name": null,
        "children": [],
        "options": {
          "__type": "ComGUIImageViewSurrogate:#EditorCommon.JsonModel.Component.GUI",
          "classname": "ImageView",
          "name": "icon_atk",
          "ZOrder": 2,
          "actiontag": 37,
          "anchorPointX": 0.5,
          "anchorPointY": 0.5,
          "classType": null,
          "colorB": 255,
          "colorG": 255,
          "colorR": 255,
          "flipX": false,
          "flipY": false,
          "height": 34,
          "ignoreSize": true,
          "layoutParameter": null,
          "opacity": 255,
          "positionPercentX": 0.106666513,
          "positionPercentY": 0.102747075,
          "positionType": 0,
          "rotation": 0,
          "scaleX": 1,
          "scaleY": 1,
          "sizePercentX": 0.533333361,
          "sizePercentY": 0.3883495,
          "sizeType": 0,
          "tag": 5,
          "touchAble": false,
          "useMergedTexture": false,
          "visible": true,
          "width": 31,
          "x": 15,
          "y": 21,
          "capInsetsHeight": 0,
          "capInsetsWidth": 0,
          "capInsetsX": 0,
          "capInsetsY": 0,
          "fileName": null,
          "fileNameData": {
            "path": "atk_icon_normal.png",
            "plistFile": "card_elem.plist",
            "resourceType": 1
          },
          "scale9Enable": false,
          "scale9Height": 34,
          "scale9Width": 31
        }
      },
      {
        "classname": "LabelAtlas",
        "name": null,
        "children": [],
        "options": {
          "__type": "ComGUILabelAtlasSurrogate:#EditorCommon.JsonModel.Component.GUI",
          "classname": "LabelAtlas",
          "name": "atk",
          "ZOrder": 2,
          "actiontag": 38,
          "anchorPointX": 0.5,
          "anchorPointY": 0.5,
          "classType": null,
          "colorB": 255,
          "colorG": 255,
          "colorR": 255,
          "flipX": false,
          "flipY": false,
          "height": 32,
          "ignoreSize": true,
          "layoutParameter": null,
          "opacity": 255,
          "positionPercentX": 0.12561579,
          "positionPercentY": 0.07595568,
          "positionType": 0,
          "rotation": 0,
          "scaleX": 0.7,
          "scaleY": 0.7,
          "sizePercentX": 1.6,
          "sizePercentY": 0.1553398,
          "sizeType": 0,
          "tag": 6,
          "touchAble": false,
          "useMergedTexture": false,
          "visible": true,
          "width": 48,
          "x": 18,
          "y": 15,
          "charMapFile": null,
          "charMapFileData": {
            "path": "GUI/labelatlasimg.png",
            "plistFile": null,
            "resourceType": 0
          },
          "itemHeight": 32,
          "itemWidth": 24,
          "startCharMap": "0",
          "stringValue": "11"
        }
      },
      {
        "classname": "ImageView",
        "name": null,
        "children": [],
        "options": {
          "__type": "ComGUIImageViewSurrogate:#EditorCommon.JsonModel.Component.GUI",
          "classname": "ImageView",
          "name": "icon_cost",
          "ZOrder": 2,
          "actiontag": 39,
          "anchorPointX": 0.5,
          "anchorPointY": 0.5,
          "classType": null,
          "colorB": 255,
          "colorG": 255,
          "colorR": 255,
          "flipX": false,
          "flipY": false,
          "height": 40,
          "ignoreSize": true,
          "layoutParameter": null,
          "opacity": 255,
          "positionPercentX": 0.105911329,
          "positionPercentY": 0.9009597,
          "positionType": 0,
          "rotation": 0,
          "scaleX": 1,
          "scaleY": 1,
          "sizePercentX": 0.533333361,
          "sizePercentY": 0.3883495,
          "sizeType": 0,
          "tag": 7,
          "touchAble": false,
          "useMergedTexture": false,
          "visible": true,
          "width": 25,
          "x": 15,
          "y": 185,
          "capInsetsHeight": 0,
          "capInsetsWidth": 0,
          "capInsetsX": 0,
          "capInsetsY": 0,
          "fileName": null,
          "fileNameData": {
            "path": "cost_icon_big.png",
            "plistFile": "card_elem.plist",
            "resourceType": 1
          },
          "scale9Enable": false,
          "scale9Height": 40,
          "scale9Width": 25
        }
      },
      {
        "classname": "LabelAtlas",
        "name": null,
        "children": [],
        "options": {
          "__type": "ComGUILabelAtlasSurrogate:#EditorCommon.JsonModel.Component.GUI",
          "classname": "LabelAtlas",
          "name": "cost",
          "ZOrder": 2,
          "actiontag": 40,
          "anchorPointX": 0.5,
          "anchorPointY": 0.5,
          "classType": null,
          "colorB": 255,
          "colorG": 255,
          "colorR": 255,
          "flipX": false,
          "flipY": false,
          "height": 32,
          "ignoreSize": true,
          "layoutParameter": null,
          "opacity": 255,
          "positionPercentX": 0.112479478,
          "positionPercentY": 0.9057424,
          "positionType": 0,
          "rotation": 0,
          "scaleX": 0.7,
          "scaleY": 0.7,
          "sizePercentX": 1.6,
          "sizePercentY": 0.1553398,
          "sizeType": 0,
          "tag": 8,
          "touchAble": false,
          "useMergedTexture": false,
          "visible": true,
          "width": 48,
          "x": 16,
          "y": 186,
          "charMapFile": null,
          "charMapFileData": {
            "path": "GUI/labelatlasimg.png",
            "plistFile": null,
            "resourceType": 0
          },
          "itemHeight": 32,
          "itemWidth": 24,
          "startCharMap": "0",
          "stringValue": "11"
        }
      },
      {
        "classname": "Label",
        "name": null,
        "children": [],
        "options": {
          "__type": "ComGUILabelSurrogate:#EditorCommon.JsonModel.Component.GUI",
          "classname": "Label",
          "name": "title",
          "ZOrder": 2,
          "actiontag": 41,
          "anchorPointX": 0.5,
          "anchorPointY": 0.5,
          "classType": null,
          "colorB": 0,
          "colorG": 0,
          "colorR": 0,
          "flipX": false,
          "flipY": false,
          "height": 27,
          "ignoreSize": true,
          "layoutParameter": null,
          "opacity": 255,
          "positionPercentX": 0.5,
          "positionPercentY": 0.377261519,
          "positionType": 1,
          "rotation": 0,
          "scaleX": 1,
          "scaleY": 1,
          "sizePercentX": 0.6333333,
          "sizePercentY": 0.131067961,
          "sizeType": 0,
          "tag": 9,
          "touchAble": false,
          "useMergedTexture": false,
          "visible": true,
          "width": 95,
          "x": 75,
          "y": 77,
          "areaHeight": 0,
          "areaWidth": 0,
          "fontFile": null,
          "fontName": "微软雅黑",
          "fontSize": 20,
          "hAlignment": 0,
          "text": "Text Label",
          "touchScaleEnable": false,
          "vAlignment": 0
        }
      },
      {
        "classname": "Label",
        "name": null,
        "children": [],
        "options": {
          "__type": "ComGUILabelSurrogate:#EditorCommon.JsonModel.Component.GUI",
          "classname": "Label",
          "name": "detail",
          "ZOrder": 2,
          "actiontag": 42,
          "anchorPointX": 0.5,
          "anchorPointY": 0.5,
          "classType": null,
          "colorB": 0,
          "colorG": 0,
          "colorR": 0,
          "flipX": false,
          "flipY": false,
          "height": 60,
          "ignoreSize": false,
          "layoutParameter": null,
          "opacity": 255,
          "positionPercentX": 0.4868639,
          "positionPercentY": 0.176390991,
          "positionType": 0,
          "rotation": 0,
          "scaleX": 1,
          "scaleY": 1,
          "sizePercentX": 0.8,
          "sizePercentY": 0.29126215,
          "sizeType": 0,
          "tag": 10,
          "touchAble": false,
          "useMergedTexture": false,
          "visible": true,
          "width": 120,
          "x": 73,
          "y": 36,
          "areaHeight": 60,
          "areaWidth": 120,
          "fontFile": null,
          "fontName": "微软雅黑",
          "fontSize": 14,
          "hAlignment": 0,
          "text": "Text Label",
          "touchScaleEnable": false,
          "vAlignment": 0
        }
      }
    ],
    "options": {
      "__type": "ComGUIPanelSurrogate:#EditorCommon.JsonModel.Component.GUI",
      "classname": "Panel",
      "name": "bg",
      "ZOrder": 0,
      "actiontag": 32,
      "anchorPointX": 0,
      "anchorPointY": 0,
      "classType": null,
      "colorB": 255,
      "colorG": 255,
      "colorR": 255,
      "flipX": false,
      "flipY": false,
      "height": 206,
      "ignoreSize": false,
      "layoutParameter": null,
      "opacity": 255,
      "positionPercentX": 0,
      "positionPercentY": 0,
      "positionType": 0,
      "rotation": 0,
      "scaleX": 1,
      "scaleY": 1,
      "sizePercentX": 1,
      "sizePercentY": 1,
      "sizeType": 0,
      "tag": 1,
      "touchAble": false,
      "useMergedTexture": false,
      "visible": true,
      "width": 150,
      "x": 0,
      "y": 0,
      "backGroundImage": null,
      "backGroundImageData": {
        "path": "card_photo_bg_big.png",
        "plistFile": "card_elem.plist",
        "resourceType": 1
      },
      "backGroundScale9Enable": false,
      "bgColorB": 255,
      "bgColorG": 200,
      "bgColorOpacity": 0,
      "bgColorR": 150,
      "bgEndColorB": 255,
      "bgEndColorG": 200,
      "bgEndColorR": 150,
      "bgStartColorB": 255,
      "bgStartColorG": 255,
      "bgStartColorR": 255,
      "capInsetsHeight": 0,
      "capInsetsWidth": 0,
      "capInsetsX": 0,
      "capInsetsY": 0,
      "clipAble": false,
      "colorType": 1,
      "layoutType": 0,
      "vectorX": 0,
      "vectorY": -0.5
    }
  }
}